Metadata-Version: 1.1
Name: testvars
Version: 1.0.0
Summary: testvars - Place-holders in complex test assertions
Home-page: https://github.com/jimfulton/testvars
Author: Jim Fulton
Author-email: jim@jimfulton.info
License: MIT
Keywords: test,testing
Platform: UNKNOWN
Classifier: Development Status :: 5 - Production/Stable
Classifier: Intended Audience :: Developers
Classifier: License :: OSI Approved :: MIT License
Classifier: Programming Language :: Python
Classifier: Programming Language :: Python :: 2
Classifier: Programming Language :: Python :: 2.7
Classifier: Programming Language :: Python :: 3
Classifier: Programming Language :: Python :: 3.4
Classifier: Programming Language :: Python :: 3.5
Classifier: Programming Language :: Python :: 3.6
